mara_app/__init__.py
mara_app/app.py
mara_app/config.py
mara_app/layout.py
mara_app/monkey_patch.py
mara_app/views.py
mara_app/.scripts/README.MD
mara_app/.scripts/check-newer.sh
mara_app/.scripts/ensure-pushed.sh
mara_app/.scripts/init.mk
mara_app/.scripts/install.mk
mara_app/.scripts/makeshell
mara_app/static/favicon.ico
mara_app/static/jquery.floatThead.min.js
mara_app/static/jquery.min.js
mara_app/static/mara.css
mara_app/static/mara.jpg
mara_app/static/mara.js
mara_app/static/bootstrap/bootstrap.min.css
mara_app/static/bootstrap/bootstrap.min.css.map
mara_app/static/bootstrap/bootstrap.min.js
mara_app/static/font-awesome-4.7.0/css/font-awesome.min.css
mara_app/static/font-awesome-4.7.0/fonts/FontAwesome.otf
mara_app/static/font-awesome-4.7.0/fonts/fontawesome-webfont.eot
mara_app/static/font-awesome-4.7.0/fonts/fontawesome-webfont.svg
mara_app/static/font-awesome-4.7.0/fonts/fontawesome-webfont.ttf
mara_app/static/font-awesome-4.7.0/fonts/fontawesome-webfont.woff
mara_app/static/font-awesome-4.7.0/fonts/fontawesome-webfont.woff2
mara_app/static/tether-1.3.3/tether.min.css
mara_app/static/tether-1.3.3/tether.min.js
mara_app-2.5.0.dist-info/LICENSE
mara_app-2.5.0.dist-info/METADATA
mara_app-2.5.0.dist-info/WHEEL
mara_app-2.5.0.dist-info/top_level.txt
mara_app-2.5.0.dist-info/RECORD
