Metadata-Version: 2.1
Name: mara-app
Version: 2.5.0
Summary: Framework for distributing flask apps across separate packages with minimal dependencies
Home-page: https://github.com/mara/mara-app
Author: Mara contributors
License: MIT
Requires-Python: >=3.6
License-File: LICENSE
Requires-Dist: mara-page >=1.7.0
Requires-Dist: mara-db >=3.0.0
Requires-Dist: flask >=1.0.2
Provides-Extra: test
Requires-Dist: pytest ; extra == 'test'
Requires-Dist: pytest-click ; extra == 'test'
